LICENSE
README.md
citation.tex
setup.py
pdb_tools_removed_atom_limit.egg-info/PKG-INFO
pdb_tools_removed_atom_limit.egg-info/SOURCES.txt
pdb_tools_removed_atom_limit.egg-info/dependency_links.txt
pdb_tools_removed_atom_limit.egg-info/entry_points.txt
pdb_tools_removed_atom_limit.egg-info/top_level.txt
pdbtools/__init__.py
pdbtools/pdb_b.py
pdbtools/pdb_chain.py
pdbtools/pdb_chainbows.py
pdbtools/pdb_chainxseg.py
pdbtools/pdb_chkensemble.py
pdbtools/pdb_delchain.py
pdbtools/pdb_delelem.py
pdbtools/pdb_delhetatm.py
pdbtools/pdb_delinsertion.py
pdbtools/pdb_delres.py
pdbtools/pdb_delresname.py
pdbtools/pdb_element.py
pdbtools/pdb_fetch.py
pdbtools/pdb_fixinsert.py
pdbtools/pdb_fromcif.py
pdbtools/pdb_gap.py
pdbtools/pdb_head.py
pdbtools/pdb_intersect.py
pdbtools/pdb_keepcoord.py
pdbtools/pdb_merge.py
pdbtools/pdb_mkensemble.py
pdbtools/pdb_occ.py
pdbtools/pdb_reatom.py
pdbtools/pdb_reres.py
pdbtools/pdb_rplchain.py
pdbtools/pdb_rplresname.py
pdbtools/pdb_seg.py
pdbtools/pdb_segxchain.py
pdbtools/pdb_selaltloc.py
pdbtools/pdb_selatom.py
pdbtools/pdb_selchain.py
pdbtools/pdb_selelem.py
pdbtools/pdb_selhetatm.py
pdbtools/pdb_selres.py
pdbtools/pdb_selresname.py
pdbtools/pdb_selseg.py
pdbtools/pdb_shiftres.py
pdbtools/pdb_sort.py
pdbtools/pdb_splitchain.py
pdbtools/pdb_splitmodel.py
pdbtools/pdb_splitseg.py
pdbtools/pdb_tidy.py
pdbtools/pdb_tocif.py
pdbtools/pdb_tofasta.py
pdbtools/pdb_uniqname.py
pdbtools/pdb_validate.py
pdbtools/pdb_wc.py