Metadata-Version: 2.1
Name: pdb-tools-removed-atom-limit
Version: 2.4.5
Summary: A swiss army knife for PDB files, customized to avoid the original atom limit.
Home-page: http://bonvinlab.org/pdb-tools
Author: Alex Morehead
Author-email: alex.morehead@gmail.com
License: Apache Software License, version 2
Project-URL: Bug Reports, https://github.com/amorehead/pdb-tools/issues
Project-URL: Source, https://github.com/amorehead/pdb-tools
Keywords: bioinformatics protein structural-biology pdb
Platform: UNKNOWN
Classifier: Development Status :: 5 - Production/Stable
Classifier: Intended Audience :: Science/Research
Classifier: Topic :: Scientific/Engineering
Classifier: Topic :: Scientific/Engineering :: Chemistry
Classifier: Topic :: Scientific/Engineering :: Bio-Informatics
Classifier: License :: OSI Approved :: Apache Software License
Classifier: Programming Language :: Python :: 2
Classifier: Programming Language :: Python :: 2.7
Classifier: Programming Language :: Python :: 3
Classifier: Programming Language :: Python :: 3.6
Classifier: Programming Language :: Python :: 3.7
License-File: LICENSE
